expenvelope/__init__.py
expenvelope/_utilities.py
expenvelope/envelope.py
expenvelope/envelope_segment.py
expenvelope/json_serializer.py
expenvelope-0.7.2.post1.dist-info/LICENSE
expenvelope-0.7.2.post1.dist-info/METADATA
expenvelope-0.7.2.post1.dist-info/WHEEL
expenvelope-0.7.2.post1.dist-info/top_level.txt
expenvelope-0.7.2.post1.dist-info/RECORD
