Metadata-Version: 2.1
Name: expenvelope
Version: 0.7.2.post1
Summary: Piecewise-exponential curves designed for musical expressiveness.
Home-page: https://git.sr.ht/~marcevanstein/expenvelope
Author: Marc Evanstein
Author-email: marc@marcevanstein.com
License: GNU GPL Version 3
Classifier: Programming Language :: Python :: 3.10
Classifier: License :: OSI Approved :: GNU General Public License v3 (GPLv3)
Classifier: Operating System :: OS Independent
Requires-Python: >=3.10
License-File: LICENSE
